unifiedllm/__init__.py
unifiedllm/unifiedcost.json
UnifiedLLM-0.1.0.dist-info/LICENSE
UnifiedLLM-0.1.0.dist-info/METADATA
UnifiedLLM-0.1.0.dist-info/WHEEL
UnifiedLLM-0.1.0.dist-info/top_level.txt
UnifiedLLM-0.1.0.dist-info/RECORD
